kinghorn/__init__.py
kinghorn/__main__.py
kinghorn/kinghorn.py
kinghorn/test_kinghorn.py
kinghorn-0.0.7.dist-info/LICENSE
kinghorn-0.0.7.dist-info/METADATA
kinghorn-0.0.7.dist-info/WHEEL
kinghorn-0.0.7.dist-info/top_level.txt
kinghorn-0.0.7.dist-info/RECORD
