Metadata-Version: 2.1
Name: kinghorn
Version: 0.0.7
Summary: Cache AWS resources
Home-page: https://github.com/TeslaGov/kinghorn
Author: Jon Crain
Author-email: jwc9412@gmail.com
License: MIT
Platform: UNKNOWN
Classifier: License :: OSI Approved :: MIT License
Classifier: Programming Language :: Python :: 3
Classifier: Programming Language :: Python :: 3.7
Requires-Dist: boto3
